{
  "channel_id": "bighead033",
  "channel_name": "빅헤드",
  "stream_start_id": "bighead033_20260618_191811",
  "stream_end_id": "bighead033_20260619_032055",
  "stream_start_time": "2026-06-18 19:18:11",
  "stream_end_time": "2026-06-19 03:20:55",
  "last_title": "모이라원챔",
  "saved_at": "2026-06-19T03:30:29.612149",
  "last_updated": "2026-06-19T03:30:29.612177",
  "update_count": 1,
  "timeline_comments": [
    {
      "comment_after_openDate": "00:00:04",
      "text": "뱅온 방제: 오늘은 그 게임을 해야겠지요",
      "description": "뱅온 방제: 오늘은 그 게임을 해야겠지요"
    },
    {
      "comment_after_openDate": "00:04:56",
      "score_difference": "74.49929469302873",
      "text": "갑자기 메? 뭐임ㅋㅋㅋ",
      "image_text": "갑자기 메? 뭐임ㅋㅋㅋ"
    },
    {
      "comment_after_openDate": "00:07:07",
      "score_difference": "31.15089948799091",
      "text": "벌써 6월이네 시간 빠르다",
      "image_text": "벌써 6월이네 시간 빠르다"
    },
    {
      "comment_after_openDate": "00:22:58",
      "score_difference": "29.231831476507214",
      "text": "종 딜 미쳤네ㅋㅋㅋ",
      "image_text": "종 딜 미쳤네ㅋㅋㅋ"
    },
    {
      "comment_after_openDate": "00:25:53",
      "score_difference": "73.10289858777526",
      "text": "안 죽는 거 실화냐 개웃기네",
      "image_text": "안 죽는 거 실화냐 개웃기네"
    },
    {
      "comment_after_openDate": "00:28:29",
      "score_difference": "34.78504940392133",
      "text": "나만의 도어맨 ㅋㅋ",
      "image_text": "나만의 도어맨 ㅋㅋ"
    },
    {
      "comment_after_openDate": "00:29:50",
      "score_difference": "31.08220088268451",
      "text": "성공하면 발로 차버리네 ㅋㅋㅋ",
      "image_text": "성공하면 발로 차버리네 ㅋㅋㅋ"
    },
    {
      "comment_after_openDate": "00:30:36",
      "score_difference": "47.040094437195975",
      "text": "또 실패했어 ㅋㅋㅋ",
      "image_text": "또 실패했어 ㅋㅋㅋ"
    },
    {
      "comment_after_openDate": "00:35:11",
      "score_difference": "47.11460466463904",
      "text": "단골손님 헤이즈 등장 ㅋㅋㅋ",
      "image_text": "단골손님 헤이즈 등장 ㅋㅋㅋ"
    },
    {
      "comment_after_openDate": "00:37:27",
      "score_difference": "62.2450512107914",
      "text": "극한의 컨셉충 도어맨 ㅋㅋㅋ",
      "image_text": "극한의 컨셉충 도어맨 ㅋㅋㅋ"
    },
    {
      "comment_after_openDate": "00:40:45",
      "score_difference": "52.10616967216917",
      "text": "직원을 왜 때려 진상 손님아 ㅋㅋㅋ",
      "image_text": "직원을 왜 때려 진상 손님아 ㅋㅋㅋ"
    },
    {
      "comment_after_openDate": "00:43:31",
      "score_difference": "32.34411001140556",
      "text": "문 뭔데 개웃기네 ㅋㅋㅋ",
      "image_text": "문 뭔데 개웃기네 ㅋㅋㅋ"
    },
    {
      "comment_after_openDate": "00:45:41",
      "score_difference": "41.62906141472389",
      "text": "감정 조종 성공적 ㄷㄷ",
      "image_text": "감정 조종 성공적 ㄷㄷ"
    },
    {
      "comment_after_openDate": "00:47:58",
      "score_difference": "40.99669573897816",
      "text": "손님 맞을래요? ㅋㅋㅋ",
      "image_text": "손님 맞을래요? ㅋㅋㅋ"
    },
    {
      "comment_after_openDate": "00:52:41",
      "score_difference": "73.30745668587939",
      "text": "와 빌드 진짜 미친건가 ㅋㅋㅋ",
      "image_text": "와 빌드 진짜 미친건가 ㅋㅋㅋ"
    },
    {
      "comment_after_openDate": "00:57:50",
      "score_difference": "51.82930257396265",
      "text": "뻘짓이랑 데이트 가라 ㅋㅋㅋ",
      "image_text": "뻘짓이랑 데이트 가라 ㅋㅋㅋ"
    },
    {
      "comment_after_openDate": "00:57:50",
      "score_difference": "29.888247406140522",
      "text": "기대 1도 안됨 ㅋㅋㅋ",
      "image_text": "기대 1도 안됨 ㅋㅋㅋ"
    },
    {
      "comment_after_openDate": "01:02:22",
      "score_difference": "38.528011001161055",
      "text": "젊을 때였으면 바로 쐈다",
      "image_text": "젊을 때였으면 바로 쐈다"
    },
    {
      "comment_after_openDate": "01:04:12",
      "score_difference": "30.57168225258151",
      "text": "와 진짜 얄밉게 잘하네 ㅋㅋㅋ",
      "image_text": "와 진짜 얄밉게 잘하네 ㅋㅋㅋ"
    },
    {
      "comment_after_openDate": "01:10:10",
      "score_difference": "43.21238688025049",
      "text": "와 궁을 씹어버리네 ㅋㅋㅋ",
      "image_text": "와 궁을 씹어버리네 ㅋㅋㅋ"
    },
    {
      "comment_after_openDate": "01:15:37",
      "score_difference": "40.60737145788568",
      "text": "호텔 가기 싫다고 ㅋㅋㅋ",
      "image_text": "호텔 가기 싫다고 ㅋㅋㅋ"
    },
    {
      "comment_after_openDate": "01:19:51",
      "score_difference": "42.12684706979303",
      "text": "칭찬에 몸을 비트네 ㅋㅋㅋ",
      "image_text": "칭찬에 몸을 비트네 ㅋㅋㅋ"
    },
    {
      "comment_after_openDate": "01:22:12",
      "score_difference": "58.92279596296754",
      "text": "이게 도탄이 아니라고?",
      "image_text": "이게 도탄이 아니라고?"
    },
    {
      "comment_after_openDate": "01:22:58",
      "score_difference": "74.74513195032725",
      "text": "6400원 날린 청년 ㅋㅋㅋ",
      "image_text": "6400원 날린 청년 ㅋㅋㅋ"
    },
    {
      "comment_after_openDate": "01:26:08",
      "score_difference": "25.32438289176552",
      "text": "돈값(사용감없음)ㅋㅋㅋㅋ",
      "image_text": "돈값(사용감없음)ㅋㅋㅋㅋ"
    },
    {
      "comment_after_openDate": "01:26:34",
      "score_difference": "33.86389588862246",
      "text": "문으로 들어갔나 ㅋㅋㅋ",
      "image_text": "문으로 들어갔나 ㅋㅋㅋ"
    },
    {
      "comment_after_openDate": "01:29:04",
      "score_difference": "34.429273986590744",
      "text": "아폴로한테 궁을ㅋㅋㅋ",
      "image_text": "아폴로한테 궁을ㅋㅋㅋ"
    },
    {
      "comment_after_openDate": "01:33:22",
      "score_difference": "48.715580819641126",
      "text": "본대 터진거 실화냐 ㅋㅋㅋ",
      "image_text": "본대 터진거 실화냐 ㅋㅋㅋ"
    },
    {
      "comment_after_openDate": "01:34:02",
      "score_difference": "73.77544942730607",
      "text": "지나가요 청년 ㅋㅋㅋ",
      "image_text": "지나가요 청년 ㅋㅋㅋ"
    },
    {
      "comment_after_openDate": "01:37:52",
      "score_difference": "46.312061901860666",
      "text": "회색화면 전문 청년ㅋㅋㅋ",
      "image_text": "회색화면 전문 청년ㅋㅋㅋ"
    },
    {
      "comment_after_openDate": "01:39:38",
      "score_difference": "63.73611222704167",
      "text": "왜 자꾸 선궁을 ㅋㅋㅋ",
      "image_text": "왜 자꾸 선궁을 ㅋㅋㅋ"
    },
    {
      "comment_after_openDate": "01:42:54",
      "score_difference": "51.89238038951168",
      "text": "화가 많이 나셨네 ㅋㅋㅋ",
      "image_text": "화가 많이 나셨네 ㅋㅋㅋ"
    },
    {
      "comment_after_openDate": "01:46:02",
      "score_difference": "42.75272969215125",
      "text": "줴줴이야 ㅋㅋㅋ",
      "image_text": "줴줴이야 ㅋㅋㅋ"
    },
    {
      "comment_after_openDate": "01:46:47",
      "score_difference": "35.29322714637616",
      "text": "칼리코가 줴줴해주네 ㅋㅋㅋ",
      "image_text": "칼리코가 줴줴해주네 ㅋㅋㅋ"
    },
    {
      "comment_after_openDate": "01:47:52",
      "score_difference": "35.652396240129",
      "text": "이거 합법 디도스임?ㅋㅋㅋ",
      "image_text": "이거 합법 디도스임?ㅋㅋㅋ"
    },
    {
      "comment_after_openDate": "01:49:41",
      "score_difference": "27.640559867164285",
      "text": "우디 탈모 ㅋㅋㅋ",
      "image_text": "우디 탈모 ㅋㅋㅋ"
    },
    {
      "comment_after_openDate": "01:56:38",
      "score_difference": "27.11301467216874",
      "text": "누가 보면 적인 줄 ㅋㅋㅋ",
      "image_text": "누가 보면 적인 줄 ㅋㅋㅋ"
    },
    {
      "comment_after_openDate": "02:00:23",
      "score_difference": "32.55961687105561",
      "text": "이게 도어맨이지 ㅋㅋㅋ",
      "image_text": "이게 도어맨이지 ㅋㅋㅋ"
    },
    {
      "comment_after_openDate": "02:04:06",
      "score_difference": "42.561239737047025",
      "text": "세븐 잘 기다렸다 ㅋㅋㅋ",
      "image_text": "세븐 잘 기다렸다 ㅋㅋㅋ"
    },
    {
      "comment_after_openDate": "02:06:28",
      "score_difference": "34.736897045458235",
      "text": "항아리로 번 거 다 잃네 ㅋㅋㅋ",
      "image_text": "항아리로 번 거 다 잃네 ㅋㅋㅋ"
    },
    {
      "comment_after_openDate": "02:07:33",
      "score_difference": "34.668648159584016",
      "text": "놀이기구 만들어주네 ㅋㅋㅋ",
      "image_text": "놀이기구 만들어주네 ㅋㅋㅋ"
    },
    {
      "comment_after_openDate": "03:20:31",
      "text": "방제 변경: 모이라원챔",
      "description": "방제 변경: 모이라원챔"
    },
    {
      "comment_after_openDate": "02:09:44",
      "score_difference": 72.01630616997275,
      "text": "군바 ㅠㅠ 몸 건강히 잘 다녀와",
      "image_text": "군바 ㅠㅠ 몸 건강히 잘 다녀와"
    },
    {
      "comment_after_openDate": "02:12:34",
      "score_difference": 38.1753873252893,
      "text": "작동 확인용 개봉 ㅋㅋㅋ 웃기네",
      "image_text": "작동 확인용 개봉 ㅋㅋㅋ 웃기네"
    },
    {
      "comment_after_openDate": "02:13:45",
      "score_difference": 35.18981558532309,
      "text": "거위알은 나라 망할 때 까야지 ㅋㅋ",
      "image_text": "거위알은 나라 망할 때 까야지 ㅋㅋ"
    },
    {
      "comment_after_openDate": "02:16:05",
      "score_difference": 35.12262297345788,
      "text": "자판기 뜯는 것도 긴장되네 ㅋㅋ",
      "image_text": "자판기 뜯는 것도 긴장되네 ㅋㅋ"
    },
    {
      "comment_after_openDate": "02:17:35",
      "score_difference": 62.415983885095734,
      "text": "영수증 길이 봐 캬 ㄷㄷ 대박",
      "image_text": "영수증 길이 봐 캬 ㄷㄷ 대박"
    },
    {
      "comment_after_openDate": "02:18:41",
      "score_difference": 72.82768507893158,
      "text": "도어맨 문단속 뭐냐고 ㅋㅋㅋ",
      "image_text": "도어맨 문단속 뭐냐고 ㅋㅋㅋ"
    },
    {
      "comment_after_openDate": "02:23:27",
      "score_difference": 75.32500096377724,
      "text": "검거 완료 ㅋㅋㅋ 호텔이었네",
      "image_text": "검거 완료 ㅋㅋㅋ 호텔이었네"
    },
    {
      "comment_after_openDate": "02:25:07",
      "score_difference": 73.56417369036308,
      "text": "기절 지옥이네 ㅋㅋㅋ 아이비 ㄷㄷ",
      "image_text": "기절 지옥이네 ㅋㅋㅋ 아이비 ㄷㄷ"
    },
    {
      "comment_after_openDate": "02:30:03",
      "score_difference": 56.42641082934709,
      "text": "4연삥은 진짜 너무하네 ㅋㅋㅋ",
      "image_text": "4연삥은 진짜 너무하네 ㅋㅋㅋ"
    },
    {
      "comment_after_openDate": "02:36:34",
      "score_difference": 35.3570705029914,
      "text": "관통 샷에 열받네 ㅋㅋㅋ 킹받",
      "image_text": "관통 샷에 열받네 ㅋㅋㅋ 킹받"
    },
    {
      "comment_after_openDate": "02:45:17",
      "score_difference": 43.54275617194994,
      "text": "슬라이딩 캬 틈새 대박 ㄷㄷ",
      "image_text": "슬라이딩 캬 틈새 대박 ㄷㄷ"
    },
    {
      "comment_after_openDate": "02:46:42",
      "score_difference": 33.12334957461276,
      "text": "순식간에 더블킬 ㄷㄷ 나이스",
      "image_text": "순식간에 더블킬 ㄷㄷ 나이스"
    },
    {
      "comment_after_openDate": "02:50:17",
      "score_difference": 48.74686757535431,
      "text": "야마토 참교육 ㅋㅋㅋ 개웃기네",
      "image_text": "야마토 참교육 ㅋㅋㅋ 개웃기네"
    },
    {
      "comment_after_openDate": "02:51:37",
      "score_difference": 73.57638989080851,
      "text": "방언 터진 래퍼 ㅋㅋㅋ 고수 뺴줘",
      "image_text": "방언 터진 래퍼 ㅋㅋㅋ 고수 뺴줘"
    },
    {
      "comment_after_openDate": "02:54:16",
      "score_difference": 53.65799759932247,
      "text": "외눈박이 마을에 두눈박이 등장 ㅋ",
      "image_text": "외눈박이 마을에 두눈박이 등장 ㅋ"
    },
    {
      "comment_after_openDate": "02:55:11",
      "score_difference": 35.01692002225322,
      "text": "건피따거 말 진짜 많네 ㅋㅋㅋ",
      "image_text": "건피따거 말 진짜 많네 ㅋㅋㅋ"
    },
    {
      "comment_after_openDate": "02:56:21",
      "score_difference": 35.765633066425195,
      "text": "2B가 왜 여기서 나와 ㅋㅋㅋ",
      "image_text": "2B가 왜 여기서 나와 ㅋㅋㅋ"
    },
    {
      "comment_after_openDate": "02:57:12",
      "score_difference": 32.43522578155258,
      "text": "유노? 영어 잘하네 ㅋㅋㅋ 렛츠고",
      "image_text": "유노? 영어 잘하네 ㅋㅋㅋ 렛츠고"
    },
    {
      "comment_after_openDate": "02:57:47",
      "score_difference": 28.527925253519456,
      "text": "조또마떼 ㅋㅋㅋ 세계 평화의 장",
      "image_text": "조또마떼 ㅋㅋㅋ 세계 평화의 장"
    },
    {
      "comment_after_openDate": "03:03:18",
      "score_difference": 48.473751956540696,
      "text": "따거 급발진 ㅋㅋㅋ C언어 터졌다",
      "image_text": "따거 급발진 ㅋㅋㅋ C언어 터졌다"
    },
    {
      "comment_after_openDate": "03:10:44",
      "score_difference": 74.0506436828976,
      "text": "소리 안 줄어드는데? 해골물 ㅋㅋㅋ",
      "image_text": "소리 안 줄어드는데? 해골물 ㅋㅋㅋ"
    },
    {
      "comment_after_openDate": "03:13:35",
      "score_difference": 41.432396440737534,
      "text": "호텔에서 의문사 ㅋㅋㅋ 왜 죽음?",
      "image_text": "호텔에서 의문사 ㅋㅋㅋ 왜 죽음?"
    },
    {
      "comment_after_openDate": "03:14:35",
      "score_difference": 42.646707325289405,
      "text": "드디어 해방이다 ㅋㅋㅋ 고생했네",
      "image_text": "드디어 해방이다 ㅋㅋㅋ 고생했네"
    },
    {
      "comment_after_openDate": "03:15:41",
      "score_difference": 34.812504655416234,
      "text": "나만 한국인이었네 ㅋㅋㅋ 뻘쭘",
      "image_text": "나만 한국인이었네 ㅋㅋㅋ 뻘쭘"
    },
    {
      "comment_after_openDate": "03:18:26",
      "score_difference": 33.88296174659467,
      "text": "부야오 샹차이 ㅋㅋㅋ 교육 방송임?",
      "image_text": "부야오 샹차이 ㅋㅋㅋ 교육 방송임?"
    },
    {
      "comment_after_openDate": "03:20:07",
      "score_difference": 35.38592829811272,
      "text": "줴줴이야 ㅋㅋㅋ 실프 납치 ㄷㄷ",
      "image_text": "줴줴이야 ㅋㅋㅋ 실프 납치 ㄷㄷ"
    },
    {
      "comment_after_openDate": "03:22:54",
      "score_difference": 32.73916643595241,
      "text": "모이라 딜구슬 머임 ㅋㅋㅋ 다 녹네",
      "image_text": "모이라 딜구슬 머임 ㅋㅋㅋ 다 녹네"
    },
    {
      "comment_after_openDate": "03:30:50",
      "score_difference": 43.491171402172995,
      "text": "힐룡인 위엄 ㄷㄷ 탱커 컷 ㅋㅋㅋ",
      "image_text": "힐룡인 위엄 ㄷㄷ 탱커 컷 ㅋㅋㅋ"
    },
    {
      "comment_after_openDate": "03:32:00",
      "score_difference": 38.02106038764457,
      "text": "캐리하면 진짜 승리지 ㅋㅋㅋ",
      "image_text": "캐리하면 진짜 승리지 ㅋㅋㅋ"
    },
    {
      "comment_after_openDate": "03:32:25",
      "score_difference": 35.61704695928643,
      "text": "야타 발차기 파괴력 보소 ㅋㅋㅋ",
      "image_text": "야타 발차기 파괴력 보소 ㅋㅋㅋ"
    },
    {
      "comment_after_openDate": "03:33:52",
      "score_difference": 40.29991230713004,
      "text": "넌 빠져 ㅋㅋㅋ 상처받겠네 ㅠㅠ",
      "image_text": "넌 빠져 ㅋㅋㅋ 상처받겠네 ㅠㅠ"
    },
    {
      "comment_after_openDate": "03:39:43",
      "score_difference": 70.71454454010187,
      "text": "이게 힐러냐? 힐루미나티 ㄷㄷ",
      "image_text": "이게 힐러냐? 힐루미나티 ㄷㄷ"
    },
    {
      "comment_after_openDate": "03:40:53",
      "score_difference": 73.67736300295206,
      "text": "점수 50점이나 줌? 억빠 대박 ㄷㄷ",
      "image_text": "점수 50점이나 줌? 억빠 대박 ㄷㄷ"
    },
    {
      "comment_after_openDate": "03:44:24",
      "score_difference": 38.7484241183587,
      "text": "부야오 샹차이 만능설 ㅋㅋㅋ",
      "image_text": "부야오 샹차이 만능설 ㅋㅋㅋ"
    },
    {
      "comment_after_openDate": "03:49:55",
      "score_difference": 70.54764664891657,
      "text": "발첩 검거 ㅋㅋㅋ 스카우트 옴?",
      "image_text": "발첩 검거 ㅋㅋㅋ 스카우트 옴?"
    },
    {
      "comment_after_openDate": "03:54:51",
      "score_difference": 52.31695651698234,
      "text": "할 말은 하는 빅카콜라 ㅋㅋㅋ",
      "image_text": "할 말은 하는 빅카콜라 ㅋㅋㅋ"
    },
    {
      "comment_after_openDate": "04:07:13",
      "score_difference": 32.88091005588079,
      "text": "모이라 통나무 캐리 ㄷㄷ 대박",
      "image_text": "모이라 통나무 캐리 ㄷㄷ 대박"
    },
    {
      "comment_after_openDate": "04:08:08",
      "score_difference": 41.99162500695407,
      "text": "와 트레 움직임 진짜 예술이네",
      "image_text": "와 트레 움직임 진짜 예술이네"
    },
    {
      "comment_after_openDate": "04:11:39",
      "score_difference": 37.91475797325563,
      "text": "이걸 밀어버리네? 모이라 사기 ㄷㄷ",
      "image_text": "이걸 밀어버리네? 모이라 사기 ㄷㄷ"
    },
    {
      "comment_after_openDate": "04:12:49",
      "score_difference": 37.54276555262945,
      "text": "개억빠맨 검거 완료 ㅋㅋㅋ 빅평",
      "image_text": "개억빠맨 검거 완료 ㅋㅋㅋ 빅평"
    },
    {
      "comment_after_openDate": "04:14:54",
      "score_difference": "33.900180056636096",
      "text": "섭딜의 신이네ㅋㅋㅋ 개잘함",
      "image_text": "섭딜의 신이네ㅋㅋㅋ 개잘함"
    },
    {
      "comment_after_openDate": "04:16:04",
      "score_difference": "36.95411436053669",
      "text": "모이라 원챔은 팀 탓 금지ㅋㅋㅋ",
      "image_text": "모이라 원챔은 팀 탓 금지ㅋㅋㅋ"
    },
    {
      "comment_after_openDate": "04:20:25",
      "score_difference": "71.07790121817017",
      "text": "와 이게 C9이 나오네 레전드ㅋㅋㅋ",
      "image_text": "와 이게 C9이 나오네 레전드ㅋㅋㅋ"
    },
    {
      "comment_after_openDate": "04:24:16",
      "score_difference": "36.01416026178482",
      "text": "트레 폼 미쳤네 ㄷㄷ",
      "image_text": "트레 폼 미쳤네 ㄷㄷ"
    },
    {
      "comment_after_openDate": "04:25:31",
      "score_difference": "44.33223795521157",
      "text": "할배요 흥분해서 던지지마요 ㅋㅋㅋ",
      "image_text": "할배요 흥분해서 던지지마요 ㅋㅋㅋ"
    },
    {
      "comment_after_openDate": "04:28:44",
      "score_difference": "50.55048655551032",
      "text": "이걸 이기네 ㅋㅋㅋ 너여!",
      "image_text": "이걸 이기네 ㅋㅋㅋ 너여!"
    },
    {
      "comment_after_openDate": "04:32:56",
      "score_difference": "36.531602581940156",
      "text": "피아노 그만 치고 나가라 ㅋㅋㅋ",
      "image_text": "피아노 그만 치고 나가라 ㅋㅋㅋ"
    },
    {
      "comment_after_openDate": "04:33:17",
      "score_difference": "26.64550163727424",
      "text": "오버워치 디테일 지리네 ㄷㄷ",
      "image_text": "오버워치 디테일 지리네 ㄷㄷ"
    },
    {
      "comment_after_openDate": "04:34:37",
      "score_difference": "38.8083713704962",
      "text": "옵치에서 파가니니 하네 ㅋㅋㅋ",
      "image_text": "옵치에서 파가니니 하네 ㅋㅋㅋ"
    },
    {
      "comment_after_openDate": "04:42:18",
      "score_difference": "37.157325236123825",
      "text": "나락 감지했네 ㅋㅋㅋㅋ",
      "image_text": "나락 감지했네 ㅋㅋㅋㅋ"
    },
    {
      "comment_after_openDate": "04:48:14",
      "score_difference": "41.215418840304885",
      "text": "역시 시온 성능 돌아버렸네 ㅋㅋㅋ",
      "image_text": "역시 시온 성능 돌아버렸네 ㅋㅋㅋ"
    },
    {
      "comment_after_openDate": "04:53:29",
      "score_difference": "35.80819822457144",
      "text": "서로 빨아주기 개웃기네 ㅋㅋㅋㅋ",
      "image_text": "서로 빨아주기 개웃기네 ㅋㅋㅋㅋ"
    },
    {
      "comment_after_openDate": "04:56:35",
      "score_difference": "38.1821989789734",
      "text": "아나 고혈압 온다 ㅋㅋㅋ",
      "image_text": "아나 고혈압 온다 ㅋㅋㅋ"
    },
    {
      "comment_after_openDate": "05:00:10",
      "score_difference": "54.70258969818076",
      "text": "힐러가 원숭이를 이기네 미친 ㄷㄷ",
      "image_text": "힐러가 원숭이를 이기네 미친 ㄷㄷ"
    },
    {
      "comment_after_openDate": "05:02:50",
      "score_difference": "57.02561602136948",
      "text": "뭔가 익숙한데 뭐지 ㅋㅋㅋ",
      "image_text": "뭔가 익숙한데 뭐지 ㅋㅋㅋ"
    },
    {
      "comment_after_openDate": "05:04:20",
      "score_difference": "40.149370621261774",
      "text": "프비공 레전드네 열어라ㅋㅋㅋ",
      "image_text": "프비공 레전드네 열어라ㅋㅋㅋ"
    },
    {
      "comment_after_openDate": "05:05:01",
      "score_difference": "37.25846125455494",
      "text": "왜요 ㅋㅋㅋ 진짜 추하네",
      "image_text": "왜요 ㅋㅋㅋ 진짜 추하네"
    },
    {
      "comment_after_openDate": "05:05:36",
      "score_difference": "40.29315810192618",
      "text": "다이아 문턱 ㄷㄷ 잘하시네",
      "image_text": "다이아 문턱 ㄷㄷ 잘하시네"
    },
    {
      "comment_after_openDate": "05:07:01",
      "score_difference": "32.60807873270903",
      "text": "들켰네 ㅋㅋㅋ 추하다 우우",
      "image_text": "들켰네 ㅋㅋㅋ 추하다 우우"
    },
    {
      "comment_after_openDate": "05:10:19",
      "score_difference": "32.70285906338007",
      "text": "힐 듀오 ㅋㅋㅋ 잼민이들",
      "image_text": "힐 듀오 ㅋㅋㅋ 잼민이들"
    },
    {
      "comment_after_openDate": "05:18:44",
      "score_difference": "31.56841174700608",
      "text": "캐서디 비냉 석양 ㄷㄷ",
      "image_text": "캐서디 비냉 석양 ㄷㄷ"
    },
    {
      "comment_after_openDate": "05:24:11",
      "score_difference": "54.03498073505061",
      "text": "치이카와 기습 비난 ㅋㅋㅋ",
      "image_text": "치이카와 기습 비난 ㅋㅋㅋ"
    },
    {
      "comment_after_openDate": "05:25:11",
      "score_difference": "61.175890115018916",
      "text": "쿠로미라니 ㅋㅋㅋ 정확하네",
      "image_text": "쿠로미라니 ㅋㅋㅋ 정확하네"
    },
    {
      "comment_after_openDate": "05:34:14",
      "score_difference": "55.971396532407866",
      "text": "순수한 마스터 귀엽네 ㅋㅋㅋ",
      "image_text": "순수한 마스터 귀엽네 ㅋㅋㅋ"
    },
    {
      "comment_after_openDate": "05:35:14",
      "score_difference": "28.783421269484055",
      "text": "자기 자신한테 억빠했네 ㅋㅋㅋ",
      "image_text": "자기 자신한테 억빠했네 ㅋㅋㅋ"
    },
    {
      "comment_after_openDate": "05:38:49",
      "score_difference": "41.25468606494511",
      "text": "트레 울어요 ㅋㅋㅋ 불쌍해",
      "image_text": "트레 울어요 ㅋㅋㅋ 불쌍해"
    },
    {
      "comment_after_openDate": "05:43:51",
      "score_difference": "40.31802236853494",
      "text": "아 ㄲㅂ 진짜 범인이네 ㅋㅋㅋ",
      "image_text": "아 ㄲㅂ 진짜 범인이네 ㅋㅋㅋ"
    },
    {
      "comment_after_openDate": "05:47:47",
      "score_difference": "42.92377700167666",
      "text": "라마 버프 미쳤네 ㅋㅋㅋㅋ",
      "image_text": "라마 버프 미쳤네 ㅋㅋㅋㅋ"
    },
    {
      "comment_after_openDate": "05:49:07",
      "score_difference": "54.204757183132116",
      "text": "진짜 됐네 ㅋㅋㅋㅋ 레전드",
      "image_text": "진짜 됐네 ㅋㅋㅋㅋ 레전드"
    },
    {
      "comment_after_openDate": "05:56:52",
      "score_difference": "33.69086957738422",
      "text": "아깝다 ㅋㅋㅋ 비상이다",
      "image_text": "아깝다 ㅋㅋㅋ 비상이다"
    },
    {
      "comment_after_openDate": "06:02:42",
      "score_difference": "49.36947533537595",
      "text": "62점 ㄷㄷ 준배치인가보네",
      "image_text": "62점 ㄷㄷ 준배치인가보네"
    },
    {
      "comment_after_openDate": "06:06:34",
      "score_difference": "44.43369259423603",
      "text": "햄찌 면허 취소급 ㅋㅋㅋ",
      "image_text": "햄찌 면허 취소급 ㅋㅋㅋ"
    },
    {
      "comment_after_openDate": "06:08:14",
      "score_difference": "58.483240458696294",
      "text": "라고 할 뻔 ㅋㅋㅋ 진짜 개웃기네",
      "image_text": "라고 할 뻔 ㅋㅋㅋ 진짜 개웃기네"
    },
    {
      "comment_after_openDate": "06:12:47",
      "score_difference": "25.526780234098016",
      "text": "밴 잘했네 아쉽다 ㅋㅋㅋ",
      "image_text": "밴 잘했네 아쉽다 ㅋㅋㅋ"
    },
    {
      "comment_after_openDate": "06:13:32",
      "score_difference": "42.76546026875811",
      "text": "오 이게 되네 ㅋㅋㅋ 대박",
      "image_text": "오 이게 되네 ㅋㅋㅋ 대박"
    },
    {
      "comment_after_openDate": "06:14:48",
      "score_difference": "47.15333716431702",
      "text": "빅황 그랩 미쳤네 ㅋㅋㅋ",
      "image_text": "빅황 그랩 미쳤네 ㅋㅋㅋ"
    },
    {
      "comment_after_openDate": "06:16:09",
      "score_difference": "44.29893153296496",
      "text": "11데스라니 즉시 덱압축 ㅋㅋㅋ",
      "image_text": "11데스라니 즉시 덱압축 ㅋㅋㅋ"
    },
    {
      "comment_after_openDate": "06:23:09",
      "score_difference": "26.74666782651673",
      "text": "밴데타 깡패네 ㅋㅋㅋ",
      "image_text": "밴데타 깡패네 ㅋㅋㅋ"
    },
    {
      "comment_after_openDate": "06:23:45",
      "score_difference": "34.24443700852507",
      "text": "남 눈치 보지 말고 해 ㅋㅋㅋ",
      "image_text": "남 눈치 보지 말고 해 ㅋㅋㅋ"
    },
    {
      "comment_after_openDate": "06:27:05",
      "score_difference": "56.96666535424034",
      "text": "딜러들 상태가 왜 이래 ㅋㅋㅋ",
      "image_text": "딜러들 상태가 왜 이래 ㅋㅋㅋ"
    },
    {
      "comment_after_openDate": "06:30:51",
      "score_difference": "35.44",
      "text": "맞밸협회 공식 인정 ㅋㅋㅋ",
      "image_text": "맞밸협회 공식 인정 ㅋㅋㅋ"
    },
    {
      "comment_after_openDate": "06:32:56",
      "score_difference": "42.16",
      "text": "와 궁 디테일 미쳤네 ㄷㄷ",
      "image_text": "와 궁 디테일 미쳤네 ㄷㄷ"
    },
    {
      "comment_after_openDate": "06:33:46",
      "score_difference": "40.65",
      "text": "이번 판 레전드 등극 ㅋㅋㅋ",
      "image_text": "이번 판 레전드 등극 ㅋㅋㅋ"
    },
    {
      "comment_after_openDate": "06:34:51",
      "score_difference": "46.59",
      "text": "젊탱 ㅋㅋㅋㅋ 별명 웃기네",
      "image_text": "젊탱 ㅋㅋㅋㅋ 별명 웃기네"
    },
    {
      "comment_after_openDate": "06:35:41",
      "score_difference": "27.38",
      "text": "하늘 나는 시그마 대참사 ㅋㅋㅋ",
      "image_text": "하늘 나는 시그마 대참사 ㅋㅋㅋ"
    },
    {
      "comment_after_openDate": "06:42:33",
      "score_difference": "56.17",
      "text": "야타 큰그림 개웃기네 ㅋㅋㅋㅋ",
      "image_text": "야타 큰그림 개웃기네 ㅋㅋㅋㅋ"
    },
    {
      "comment_after_openDate": "06:44:54",
      "score_difference": "38.75",
      "text": "에임 넘사벽이다 진짜",
      "image_text": "에임 넘사벽이다 진짜"
    },
    {
      "comment_after_openDate": "06:45:54",
      "score_difference": "30.75",
      "text": "중고대전 1황 클라스 ㅋㅋㅋ",
      "image_text": "중고대전 1황 클라스 ㅋㅋㅋ"
    },
    {
      "comment_after_openDate": "06:48:49",
      "score_difference": "36.53",
      "text": "매칭 주작 아니냐 ㅋㅋㅋ",
      "image_text": "매칭 주작 아니냐 ㅋㅋㅋ"
    },
    {
      "comment_after_openDate": "06:51:01",
      "score_difference": "33.34",
      "text": "도미나 피지컬 괴물인가 ㄷㄷ",
      "image_text": "도미나 피지컬 괴물인가 ㄷㄷ"
    },
    {
      "comment_after_openDate": "06:51:36",
      "score_difference": "54.52",
      "text": "새벽 PC방 초딩 빌런 ㅋㅋ",
      "image_text": "새벽 PC방 초딩 빌런 ㅋㅋ"
    },
    {
      "comment_after_openDate": "06:52:37",
      "score_difference": "31.30",
      "text": "힐차이로 죽은 거 실화냐 ㅋㅋㅋ",
      "image_text": "힐차이로 죽은 거 실화냐 ㅋㅋㅋ"
    },
    {
      "comment_after_openDate": "06:57:37",
      "score_difference": "73.43",
      "text": "에임 지렸다 ㅋㅋㅋㅋ",
      "image_text": "에임 지렸다 ㅋㅋㅋㅋ"
    },
    {
      "comment_after_openDate": "06:58:39",
      "score_difference": "34.31",
      "text": "자책형 딜러 ㅋㅋㅋㅋ 말투 대박",
      "image_text": "자책형 딜러 ㅋㅋㅋㅋ 말투 대박"
    },
    {
      "comment_after_openDate": "06:59:04",
      "score_difference": "36.22",
      "text": "세계선 비틀기 ㅋㅋㅋㅋㅋ",
      "image_text": "세계선 비틀기 ㅋㅋㅋㅋㅋ"
    },
    {
      "comment_after_openDate": "07:00:19",
      "score_difference": "54.01",
      "text": "캬 와캬퍄 미쳤다",
      "image_text": "캬 와캬퍄 미쳤다"
    },
    {
      "comment_after_openDate": "07:01:45",
      "score_difference": "42.87",
      "text": "삼촌 쩀민이 듀오 ㅋㅋㅋ",
      "image_text": "삼촌 쩀민이 듀오 ㅋㅋㅋ"
    },
    {
      "comment_after_openDate": "07:08:51",
      "score_difference": "50.39",
      "text": "속죄형 딜러 등장 ㅋㅋㅋ",
      "image_text": "속죄형 딜러 등장 ㅋㅋㅋ"
    },
    {
      "comment_after_openDate": "07:09:36",
      "score_difference": "66.78",
      "text": "치아바타는 빵이잖아 ㅋㅋㅋㅋ",
      "image_text": "치아바타는 빵이잖아 ㅋㅋㅋㅋ"
    },
    {
      "comment_after_openDate": "07:12:57",
      "score_difference": "53.32",
      "text": "다이아는 도대체 어떤 곳일까 ㅋㅋㅋ",
      "image_text": "다이아는 도대체 어떤 곳일까 ㅋㅋㅋ"
    },
    {
      "comment_after_openDate": "07:13:57",
      "score_difference": "47.88",
      "text": "멘헤라 딜러 결국 터졌네 ㅋㅋㅋ",
      "image_text": "멘헤라 딜러 결국 터졌네 ㅋㅋㅋ"
    },
    {
      "comment_after_openDate": "07:19:09",
      "score_difference": "35.01",
      "text": "벌레 잡는 건 확실하네 ㅋㅋ",
      "image_text": "벌레 잡는 건 확실하네 ㅋㅋ"
    },
    {
      "comment_after_openDate": "07:19:34",
      "score_difference": "43.39",
      "text": "정신병자 마인드 ㅋㅋㅋㅋ",
      "image_text": "정신병자 마인드 ㅋㅋㅋㅋ"
    },
    {
      "comment_after_openDate": "07:23:44",
      "score_difference": "33.47",
      "text": "러카콜라 ㅋㅋㅋㅋ 멘헤라 오지네",
      "image_text": "러카콜라 ㅋㅋㅋㅋ 멘헤라 오지네"
    },
    {
      "comment_after_openDate": "07:26:40",
      "score_difference": "57.16",
      "text": "옵평 수준 실화냐 ㅋㅋㅋㅋ",
      "image_text": "옵평 수준 실화냐 ㅋㅋㅋㅋ"
    },
    {
      "comment_after_openDate": "07:29:40",
      "score_difference": "28.90",
      "text": "대본 있는 경기 ㅋㅋㅋ",
      "image_text": "대본 있는 경기 ㅋㅋㅋ"
    },
    {
      "comment_after_openDate": "07:30:30",
      "score_difference": "37.37",
      "text": "정신병은 이유가 없다 ㅋㅋㅋ",
      "image_text": "정신병은 이유가 없다 ㅋㅋㅋ"
    },
    {
      "comment_after_openDate": "07:32:16",
      "score_difference": "50.30",
      "text": "퍼즈락 ㅋㅋㅋㅋㅋ 역시 신사의 게임",
      "image_text": "퍼즈락 ㅋㅋㅋㅋㅋ 역시 신사의 게임"
    },
    {
      "comment_after_openDate": "07:33:51",
      "score_difference": "72.82",
      "text": "패작 원숭이 참교육 ㅋㅋㅋ",
      "image_text": "패작 원숭이 참교육 ㅋㅋㅋ"
    },
    {
      "comment_after_openDate": "07:43:02",
      "score_difference": "67.65",
      "text": "태권도 챔피언 ㅋㅋㅋ 무술 GOAT",
      "image_text": "태권도 챔피언 ㅋㅋㅋ 무술 GOAT"
    },
    {
      "comment_after_openDate": "07:55:37",
      "score_difference": "73.48",
      "text": "마스터 못 간 이유 확실하네 ㅋㅋㅋ",
      "image_text": "마스터 못 간 이유 확실하네 ㅋㅋㅋ"
    },
    {
      "comment_after_openDate": "08:00:04",
      "score_difference": "46.33",
      "text": "오늘도 빅바~ ㅋㅋㅋ",
      "image_text": "오늘도 빅바~ ㅋㅋㅋ"
    },
    {
      "comment_after_openDate": "08:01:30",
      "score_difference": "34.40",
      "text": "이스케이프 프롬 걸스 ㅋㅋㅋ",
      "image_text": "이스케이프 프롬 걸스 ㅋㅋㅋ"
    }
  ],
  "statistics": {
    "total_highlights": 155,
    "total_with_scores": 153,
    "avg_score": 44.96,
    "max_score": 75.33,
    "min_score": 25.32,
    "big_highlights": 18,
    "score_ranges": {
      "0-20": 0,
      "21-40": 69,
      "41-60": 60,
      "61-80": 24,
      "81-100": 0
    }
  }
}