{
  "channel_id": "dokkhye",
  "channel_name": "독고혜지_WAK",
  "stream_start_id": "dokkhye_20260513_153833",
  "stream_end_id": "dokkhye_20260513_214247",
  "stream_start_time": "2026-05-13 15:38:33",
  "stream_end_time": "2026-05-13 21:42:47",
  "last_title": "고로나 ㅇㅅㅇ 걸려버림 3기 1화 부터 ~ ",
  "saved_at": "2026-05-13T21:44:43.469612",
  "last_updated": "2026-05-13T21:44:43.469621",
  "update_count": 1,
  "timeline_comments": [
    {
      "comment_after_openDate": "00:00:00",
      "text": "뱅온 방제: ㅇㅅㅇ 방송 9시간만에 다시키기.",
      "description": "뱅온 방제: ㅇㅅㅇ 방송 9시간만에 다시키기."
    },
    {
      "comment_after_openDate": "01:15:58",
      "text": "방제 변경: 고로 거울치료하기 메이저 2기 23화부터 ~ ",
      "description": "방제 변경: 고로 거울치료하기 메이저 2기 23화부터 ~ "
    },
    {
      "comment_after_openDate": "02:03:38",
      "text": "방제 변경: 에겐야구 하지마!!!  메이저 2기 23화부터 ~ ",
      "description": "방제 변경: 에겐야구 하지마!!!  메이저 2기 23화부터 ~ "
    },
    {
      "comment_after_openDate": "00:14:05",
      "score_difference": 57.22428957357947,
      "text": "11시 기상 실화냐 ㅋㅋㅋ",
      "image_text": "11시 기상 실화냐 ㅋㅋㅋ"
    },
    {
      "comment_after_openDate": "00:15:56",
      "score_difference": 53.94667015181014,
      "text": "금쪽이 거울치료 레전드",
      "image_text": "금쪽이 거울치료 레전드"
    },
    {
      "comment_after_openDate": "00:18:01",
      "score_difference": 49.86187360847727,
      "text": "와 이거 개꿀잼일듯 ㄷㄷ",
      "image_text": "와 이거 개꿀잼일듯 ㄷㄷ"
    },
    {
      "comment_after_openDate": "00:22:06",
      "score_difference": 39.20014850378462,
      "text": "설마 하루 휴뱅각? ㅋㅋㅋ",
      "image_text": "설마 하루 휴뱅각? ㅋㅋㅋ"
    },
    {
      "comment_after_openDate": "00:25:27",
      "score_difference": 75.05401851846064,
      "text": "선구리 ㅈㄴ 잘어울림 ㅋㅋㅋ",
      "image_text": "선구리 ㅈㄴ 잘어울림 ㅋㅋㅋ"
    },
    {
      "comment_after_openDate": "00:26:47",
      "score_difference": 32.44000318559523,
      "text": "똥겜패에 혜지 조합 ㄷㄷ",
      "image_text": "똥겜패에 혜지 조합 ㄷㄷ"
    },
    {
      "comment_after_openDate": "00:28:04",
      "score_difference": 38.84915479197697,
      "text": "졸린 목소리 킹받네 ㅋㅋㅋ",
      "image_text": "졸린 목소리 킹받네 ㅋㅋㅋ"
    },
    {
      "comment_after_openDate": "00:31:09",
      "score_difference": 49.09714490441762,
      "text": "결국 정체 깠네 ㅋㅋㅋ",
      "image_text": "결국 정체 깠네 ㅋㅋㅋ"
    },
    {
      "comment_after_openDate": "00:33:20",
      "score_difference": 36.530882562656075,
      "text": "리액션 ㄹㅇ 개웃김 ㅋㅋㅋ",
      "image_text": "리액션 ㄹㅇ 개웃김 ㅋㅋㅋ"
    },
    {
      "comment_after_openDate": "00:35:15",
      "score_difference": 32.24099999462082,
      "text": "돈 아까워서 참는 중 ㅋㅋㅋ",
      "image_text": "돈 아까워서 참는 중 ㅋㅋㅋ"
    },
    {
      "comment_after_openDate": "00:35:15",
      "score_difference": 37.74231644568994,
      "text": "아바타 꼬라지 진짜 ㅋㅋㅋ",
      "image_text": "아바타 꼬라지 진짜 ㅋㅋㅋ"
    },
    {
      "comment_after_openDate": "00:37:40",
      "score_difference": 40.07807105100086,
      "text": "스폰지밥 캐릭터 닮음 ㅋㅋㅋ",
      "image_text": "스폰지밥 캐릭터 닮음 ㅋㅋㅋ"
    },
    {
      "comment_after_openDate": "00:41:31",
      "score_difference": 35.20124364351939,
      "text": "웃자마자 바로 들키네 ㅋㅋㅋ",
      "image_text": "웃자마자 바로 들키네 ㅋㅋㅋ"
    },
    {
      "comment_after_openDate": "00:44:36",
      "score_difference": 33.6055160290243,
      "text": "연봉이 5점 만점에 6점 ㄷㄷ",
      "image_text": "연봉이 5점 만점에 6점 ㄷㄷ"
    },
    {
      "comment_after_openDate": "00:49:49",
      "score_difference": 40.57710158048326,
      "text": "위로 10살은 너무 떨인데",
      "image_text": "위로 10살은 너무 떨인데"
    },
    {
      "comment_after_openDate": "00:52:45",
      "score_difference": 72.41336765977856,
      "text": "개취존중 좀 해줘라 ㅋㅋㅋ",
      "image_text": "개취존중 좀 해줘라 ㅋㅋㅋ"
    },
    {
      "comment_after_openDate": "00:54:38",
      "score_difference": 74.63737001775895,
      "text": "시미켄 소식에 헉 도배 ㄷㄷ",
      "image_text": "시미켄 소식에 헉 도배 ㄷㄷ"
    },
    {
      "comment_after_openDate": "01:01:46",
      "score_difference": 34.92737373417778,
      "text": "정형땅땅 데려가라 ㅋㅋㅋ",
      "image_text": "정형땅땅 데려가라 ㅋㅋㅋ"
    },
    {
      "comment_after_openDate": "01:03:17",
      "score_difference": 43.23857255767835,
      "text": "여자니까 가능한 거임 ㄷㄷ",
      "image_text": "여자니까 가능한 거임 ㄷㄷ"
    },
    {
      "comment_after_openDate": "01:04:02",
      "score_difference": 47.005953945064114,
      "text": "결혼식 등신대 에바 ㅋㅋㅋ",
      "image_text": "결혼식 등신대 에바 ㅋㅋㅋ"
    },
    {
      "comment_after_openDate": "01:05:47",
      "score_difference": 43.0491907944262,
      "text": "생활패턴 반대면 힘들지",
      "image_text": "생활패턴 반대면 힘들지"
    },
    {
      "comment_after_openDate": "01:06:58",
      "score_difference": 73.61722388933045,
      "text": "갑자기 분위기 뭣? ㅋㅋㅋ",
      "image_text": "갑자기 분위기 뭣? ㅋㅋㅋ"
    },
    {
      "comment_after_openDate": "01:09:04",
      "score_difference": 30.857079349548005,
      "text": "세구랑 뢴트 합방 기대됨",
      "image_text": "세구랑 뢴트 합방 기대됨"
    },
    {
      "comment_after_openDate": "01:13:52",
      "score_difference": 36.55789450716175,
      "text": "지루할 틈이 없네 ㅋㅋㅋ",
      "image_text": "지루할 틈이 없네 ㅋㅋㅋ"
    },
    {
      "comment_after_openDate": "01:24:00",
      "score_difference": 31.827776246274922,
      "text": "졸다가 기억 삭제 ㅋㅋㅋ",
      "image_text": "졸다가 기억 삭제 ㅋㅋㅋ"
    },
    {
      "comment_after_openDate": "01:25:50",
      "score_difference": 73.85952167621356,
      "text": "도파민 중독자 레전드 ㄷㄷ",
      "image_text": "도파민 중독자 레전드 ㄷㄷ"
    },
    {
      "comment_after_openDate": "01:28:30",
      "score_difference": 44.802858053454095,
      "text": "자이로볼 속도로 넘어감",
      "image_text": "자이로볼 속도로 넘어감"
    },
    {
      "comment_after_openDate": "01:31:42",
      "score_difference": 64.08059950299446,
      "text": "눈 왜 저래 ㅋㅋㅋ 작붕임?",
      "image_text": "눈 왜 저래 ㅋㅋㅋ 작붕임?"
    },
    {
      "comment_after_openDate": "01:38:31",
      "score_difference": 34.17807668468795,
      "text": "아빠가 전투력 측정기임?",
      "image_text": "아빠가 전투력 측정기임?"
    },
    {
      "comment_after_openDate": "01:39:37",
      "score_difference": 40.791540859490965,
      "text": "1군 이기면 자퇴 ㅋㅋㅋ",
      "image_text": "1군 이기면 자퇴 ㅋㅋㅋ"
    },
    {
      "comment_after_openDate": "01:43:28",
      "score_difference": 42.65234440921962,
      "text": "송구 스무스한 거 보소",
      "image_text": "송구 스무스한 거 보소"
    },
    {
      "comment_after_openDate": "01:44:18",
      "score_difference": 45.598371025845715,
      "text": "이게 오타니야 조 깁슨이야",
      "image_text": "이게 오타니야 조 깁슨이야"
    },
    {
      "comment_after_openDate": "01:51:49",
      "score_difference": 49.48914051732403,
      "text": "여장남자 캐릭터 뭐냐고",
      "image_text": "여장남자 캐릭터 뭐냐고"
    },
    {
      "comment_after_openDate": "01:53:45",
      "score_difference": 31.074793194917916,
      "text": "중학교 때 절교 썰 ㅋㅋㅋ",
      "image_text": "중학교 때 절교 썰 ㅋㅋㅋ"
    },
    {
      "comment_after_openDate": "01:57:10",
      "score_difference": 46.33517607392676,
      "text": "고멤 오디션 1차 비주얼",
      "image_text": "고멤 오디션 1차 비주얼"
    },
    {
      "comment_after_openDate": "01:59:26",
      "score_difference": 30.894180351622992,
      "text": "진짜 오타니 그 자체 ㄷㄷ",
      "image_text": "진짜 오타니 그 자체 ㄷㄷ"
    },
    {
      "comment_after_openDate": "02:00:51",
      "score_difference": 31.279575860419065,
      "text": "제목 다 에겐이야 ㅋㅋㅋ",
      "image_text": "제목 다 에겐이야 ㅋㅋㅋ"
    },
    {
      "comment_after_openDate": "02:01:41",
      "score_difference": 41.78082487062672,
      "text": "허세 레전드 찍네 ㅋㅋㅋ",
      "image_text": "허세 레전드 찍네 ㅋㅋㅋ"
    },
    {
      "comment_after_openDate": "02:03:21",
      "score_difference": 42.08411251984024,
      "text": "코모리한테 맞아야 정신차림",
      "image_text": "코모리한테 맞아야 정신차림"
    },
    {
      "comment_after_openDate": "02:04:12",
      "score_difference": 74.99439442300924,
      "text": "150키로 데드볼 ㄷㄷ",
      "image_text": "150키로 데드볼 ㄷㄷ"
    },
    {
      "comment_after_openDate": "02:16:21",
      "text": "방제 변경: 사토!! 넌 고로한테 가스라이팅 당하고 있는거야!! 메이저 2기 23화부터 ~ ",
      "description": "방제 변경: 사토!! 넌 고로한테 가스라이팅 당하고 있는거야!! 메이저 2기 23화부터 ~ "
    },
    {
      "comment_after_openDate": "02:37:35",
      "text": "방제 변경: 고로나 ㅇㅅㅇ 걸려버림 3기 1화 부터 ~ ",
      "description": "방제 변경: 고로나 ㅇㅅㅇ 걸려버림 3기 1화 부터 ~ "
    },
    {
      "comment_after_openDate": "02:08:17",
      "score_difference": "48.62552852602684",
      "text": "몇개월 참았다니 대단 ㅋㅋㅋ",
      "image_text": "몇개월 참았다니 대단 ㅋㅋㅋ"
    },
    {
      "comment_after_openDate": "02:11:56",
      "score_difference": "25.73699181115854",
      "text": "홍머병 ㄹㅇ 웃기네 ㅋㅋ",
      "image_text": "홍머병 ㄹㅇ 웃기네 ㅋㅋ"
    },
    {
      "comment_after_openDate": "02:17:30",
      "score_difference": "52.17192089779836",
      "text": "역시 정실은 다르네 ㅋㅋ",
      "image_text": "역시 정실은 다르네 ㅋㅋ"
    },
    {
      "comment_after_openDate": "02:23:26",
      "score_difference": "34.372842675833255",
      "text": "ㅋㅋㅋㅋ 이상형 왜저래",
      "image_text": "ㅋㅋㅋㅋ 이상형 왜저래"
    },
    {
      "comment_after_openDate": "02:32:15",
      "score_difference": "42.38684024893448",
      "text": "멘헤라 각성 ㅋㅋㅋㅋ",
      "image_text": "멘헤라 각성 ㅋㅋㅋㅋ"
    },
    {
      "comment_after_openDate": "02:34:50",
      "score_difference": "75.54622324434058",
      "text": "와 1군 박살내는 거 소름",
      "image_text": "와 1군 박살내는 거 소름"
    },
    {
      "comment_after_openDate": "02:34:50",
      "score_difference": "39.22277928883531",
      "text": "홈런 한 방에 치료완료 ㅋㅋ",
      "image_text": "홈런 한 방에 치료완료 ㅋㅋ"
    },
    {
      "comment_after_openDate": "02:36:56",
      "score_difference": "61.11230478382716",
      "text": "이게 2기 끝이라고? ㄷㄷ",
      "image_text": "이게 2기 끝이라고? ㄷㄷ"
    },
    {
      "comment_after_openDate": "02:39:16",
      "score_difference": "33.615026253225125",
      "text": "1군 컷! 깔끔하네 ㅋㅋㅋ",
      "image_text": "1군 컷! 깔끔하네 ㅋㅋㅋ"
    },
    {
      "comment_after_openDate": "02:41:36",
      "score_difference": "57.373027303469634",
      "text": "작화 업그레이드 실화냐 ㅋㅋ",
      "image_text": "작화 업그레이드 실화냐 ㅋㅋ"
    },
    {
      "comment_after_openDate": "02:46:47",
      "score_difference": "29.067978380386833",
      "text": "코모링 4번 타자 듬직하다",
      "image_text": "코모링 4번 타자 듬직하다"
    },
    {
      "comment_after_openDate": "02:49:03",
      "score_difference": "26.27528038460061",
      "text": "엄마 속타는 소리 들림 ㅋㅋ",
      "image_text": "엄마 속타는 소리 들림 ㅋㅋ"
    },
    {
      "comment_after_openDate": "02:50:08",
      "score_difference": "32.585987299852405",
      "text": "엄마 반응 리얼하네 ㅋㅋ",
      "image_text": "엄마 반응 리얼하네 ㅋㅋ"
    },
    {
      "comment_after_openDate": "02:50:53",
      "score_difference": "32.63405269449123",
      "text": "사회 쓴맛 좀 봐라 ㅋㅋㅋ",
      "image_text": "사회 쓴맛 좀 봐라 ㅋㅋㅋ"
    },
    {
      "comment_after_openDate": "02:58:39",
      "score_difference": "34.46517557943957",
      "text": "머리에 야구공만 들었나 봐",
      "image_text": "머리에 야구공만 들었나 봐"
    },
    {
      "comment_after_openDate": "03:04:21",
      "score_difference": "52.59248571754287",
      "text": "완전 청춘물 엔딩 ㅋㅋㅋ",
      "image_text": "완전 청춘물 엔딩 ㅋㅋㅋ"
    },
    {
      "comment_after_openDate": "03:05:11",
      "score_difference": "36.115384787396266",
      "text": "신작 야구 애니 느낌 나네",
      "image_text": "신작 야구 애니 느낌 나네"
    },
    {
      "comment_after_openDate": "03:07:38",
      "score_difference": "54.515565879858165",
      "text": "와우 전파하는 것 같네 ㅋㅋ",
      "image_text": "와우 전파하는 것 같네 ㅋㅋ"
    },
    {
      "comment_after_openDate": "03:08:28",
      "score_difference": "36.00595591470375",
      "text": "안경 쓰니 코난 같네 ㅋㅋ",
      "image_text": "안경 쓰니 코난 같네 ㅋㅋ"
    },
    {
      "comment_after_openDate": "03:12:19",
      "score_difference": "63.27219324306972",
      "text": "고딩들 유치한 거 개웃김",
      "image_text": "고딩들 유치한 거 개웃김"
    },
    {
      "comment_after_openDate": "03:15:39",
      "score_difference": "38.068921249894274",
      "text": "완전 스포츠물 정석이네",
      "image_text": "완전 스포츠물 정석이네"
    },
    {
      "comment_after_openDate": "03:19:30",
      "score_difference": "40.419953521941295",
      "text": "삼각관계 시작인가요? ㅋㅋ",
      "image_text": "삼각관계 시작인가요? ㅋㅋ"
    },
    {
      "comment_after_openDate": "03:23:53",
      "score_difference": "30.172778269967544",
      "text": "시미즈한테 전력투구 뭐임",
      "image_text": "시미즈한테 전력투구 뭐임"
    },
    {
      "comment_after_openDate": "03:27:00",
      "score_difference": "71.91072616837812",
      "text": "야스라이팅 지대로네 ㅋㅋ",
      "image_text": "야스라이팅 지대로네 ㅋㅋ"
    },
    {
      "comment_after_openDate": "03:32:05",
      "score_difference": "35.320164881412225",
      "text": "현실 야구 고증 지리네 ㄷㄷ",
      "image_text": "현실 야구 고증 지리네 ㄷㄷ"
    },
    {
      "comment_after_openDate": "03:33:35",
      "score_difference": "27.887426419722527",
      "text": "설마 전여친? 분위기 뭐냐",
      "image_text": "설마 전여친? 분위기 뭐냐"
    },
    {
      "comment_after_openDate": "03:35:40",
      "score_difference": "45.21878522853384",
      "text": "토황 등장 ㅋㅋㅋㅋㅋㅋㅋㅋ",
      "image_text": "토황 등장 ㅋㅋㅋㅋㅋㅋㅋㅋ"
    },
    {
      "comment_after_openDate": "03:48:04",
      "score_difference": "28.709794896415225",
      "text": "말하는 거 팩폭 오지네 ㅋㅋ",
      "image_text": "말하는 거 팩폭 오지네 ㅋㅋ"
    },
    {
      "comment_after_openDate": "03:49:20",
      "score_difference": "32.7357312142524",
      "text": "첫 경기부터 명문고 실화?",
      "image_text": "첫 경기부터 명문고 실화?"
    },
    {
      "comment_after_openDate": "03:55:13",
      "score_difference": "51.515978152251215",
      "text": "150을 어떻게 잡는 거야",
      "image_text": "150을 어떻게 잡는 거야"
    },
    {
      "comment_after_openDate": "04:05:21",
      "score_difference": "26.741184704965644",
      "text": "시작부터 고구마 답답하네",
      "image_text": "시작부터 고구마 답답하네"
    },
    {
      "comment_after_openDate": "04:07:32",
      "score_difference": "40.4955925211004",
      "text": "더티 야구 시작됐네 ㅋㅋㅋ",
      "image_text": "더티 야구 시작됐네 ㅋㅋㅋ"
    },
    {
      "comment_after_openDate": "04:11:16",
      "score_difference": "33.769163652608874",
      "text": "오타니가 하자면 바로 하지",
      "image_text": "오타니가 하자면 바로 하지"
    },
    {
      "comment_after_openDate": "04:12:51",
      "score_difference": "28.285704373199408",
      "text": "오타니 드립 ㅋㅋㅋㅋㅋ",
      "image_text": "오타니 드립 ㅋㅋㅋㅋㅋ"
    },
    {
      "comment_after_openDate": "04:13:41",
      "score_difference": "26.31119730033263",
      "text": "진구 같이 생겨서 왜 저래",
      "image_text": "진구 같이 생겨서 왜 저래"
    },
    {
      "comment_after_openDate": "04:17:20",
      "score_difference": "37.83408346556705",
      "text": "아마추어가 잡기엔 무리지",
      "image_text": "아마추어가 잡기엔 무리지"
    },
    {
      "comment_after_openDate": "04:19:47",
      "score_difference": "59.82782397856094",
      "text": "빨래질 제대로 됐네 ㅋㅋㅋ",
      "image_text": "빨래질 제대로 됐네 ㅋㅋㅋ"
    },
    {
      "comment_after_openDate": "04:21:53",
      "score_difference": "26.879554871561055",
      "text": "세탁 속도 5G급이네 ㅋㅋ",
      "image_text": "세탁 속도 5G급이네 ㅋㅋ"
    },
    {
      "comment_after_openDate": "04:23:03",
      "score_difference": "47.47143960674522",
      "text": "또 심술 부리기 시작함 ㅋㅋ",
      "image_text": "또 심술 부리기 시작함 ㅋㅋ"
    },
    {
      "comment_after_openDate": "04:23:53",
      "score_difference": "37.29300336702191",
      "text": "완전 군대 삽질 느낌이네",
      "image_text": "완전 군대 삽질 느낌이네"
    },
    {
      "comment_after_openDate": "04:28:52",
      "score_difference": "40.14",
      "text": "자갈 고르기 힘들어 보이네 ㅋㅋㅋ",
      "image_text": "자갈 고르기 힘들어 보이네 ㅋㅋㅋ"
    },
    {
      "comment_after_openDate": "04:32:28",
      "score_difference": "34.01",
      "text": "츤데레 반응 실화냐 ㅋㅋㅋ",
      "image_text": "츤데레 반응 실화냐 ㅋㅋㅋ"
    },
    {
      "comment_after_openDate": "04:36:17",
      "score_difference": "72.56",
      "text": "진짜 아빠 등장? 화력 보소 ㄷㄷ",
      "image_text": "진짜 아빠 등장? 화력 보소 ㄷㄷ"
    },
    {
      "comment_after_openDate": "04:37:52",
      "score_difference": "34.78",
      "text": "훈련 빡세게 굴리네 ㅋㅋㅋ",
      "image_text": "훈련 빡세게 굴리네 ㅋㅋㅋ"
    },
    {
      "comment_after_openDate": "04:43:47",
      "score_difference": "45.07",
      "text": "스탯 초기화는 선 넘었지 ㅋㅋ",
      "image_text": "스탯 초기화는 선 넘었지 ㅋㅋ"
    },
    {
      "comment_after_openDate": "04:47:21",
      "score_difference": "40.41",
      "text": "멘탈 하나는 끝내주네 ㅋㅋ",
      "image_text": "멘탈 하나는 끝내주네 ㅋㅋ"
    },
    {
      "comment_after_openDate": "04:48:51",
      "score_difference": "51.03",
      "text": "고로가 부장 맡는 게 맞지",
      "image_text": "고로가 부장 맡는 게 맞지"
    },
    {
      "comment_after_openDate": "04:50:41",
      "score_difference": "45.02",
      "text": "암구호 귀엽네 ㅋㅋㅋ",
      "image_text": "암구호 귀엽네 ㅋㅋㅋ"
    },
    {
      "comment_after_openDate": "04:52:26",
      "score_difference": "33.41",
      "text": "비실이 삐진 거 킹받네 ㅋㅋ",
      "image_text": "비실이 삐진 거 킹받네 ㅋㅋ"
    },
    {
      "comment_after_openDate": "04:54:57",
      "score_difference": "40.64",
      "text": "고멤 조기교육 대성공 ㅋㅋ",
      "image_text": "고멤 조기교육 대성공 ㅋㅋ"
    },
    {
      "comment_after_openDate": "04:57:30",
      "score_difference": "39.62",
      "text": "전개 속도 실화냐 ㄷㄷ",
      "image_text": "전개 속도 실화냐 ㄷㄷ"
    },
    {
      "comment_after_openDate": "05:03:19",
      "score_difference": "30.27",
      "text": "중딩이 왤케 건방져 ㅋㅋㅋ",
      "image_text": "중딩이 왤케 건방져 ㅋㅋㅋ"
    },
    {
      "comment_after_openDate": "05:04:14",
      "score_difference": "30.43",
      "text": "실력 있으니 건방질만 하네 ㅋㅋ",
      "image_text": "실력 있으니 건방질만 하네 ㅋㅋ"
    },
    {
      "comment_after_openDate": "05:06:57",
      "score_difference": "29.46",
      "text": "번트 대는 실력 보소 캬",
      "image_text": "번트 대는 실력 보소 캬"
    },
    {
      "comment_after_openDate": "05:08:52",
      "score_difference": "39.10",
      "text": "말로는 하지 말라면서 ㅋㅋㅋ",
      "image_text": "말로는 하지 말라면서 ㅋㅋㅋ"
    },
    {
      "comment_after_openDate": "05:10:22",
      "score_difference": "37.72",
      "text": "얼굴부터 고집 있어 보임 ㅋㅋ",
      "image_text": "얼굴부터 고집 있어 보임 ㅋㅋ"
    },
    {
      "comment_after_openDate": "05:13:25",
      "score_difference": "32.94",
      "text": "자신감 하나는 우주급이네",
      "image_text": "자신감 하나는 우주급이네"
    },
    {
      "comment_after_openDate": "05:19:10",
      "score_difference": "45.04",
      "text": "음흉한 표정 킹받네 ㅋㅋㅋ",
      "image_text": "음흉한 표정 킹받네 ㅋㅋㅋ"
    },
    {
      "comment_after_openDate": "05:22:05",
      "score_difference": "30.75",
      "text": "역시 유전자는 못 속인다",
      "image_text": "역시 유전자는 못 속인다"
    },
    {
      "comment_after_openDate": "05:23:00",
      "score_difference": "49.95",
      "text": "그리기 귀찮았던 거 아니냐 ㅋㅋ",
      "image_text": "그리기 귀찮았던 거 아니냐 ㅋㅋ"
    },
    {
      "comment_after_openDate": "05:25:46",
      "score_difference": "32.86",
      "text": "갑자기 분위기 고급 야구 ㄷㄷ",
      "image_text": "갑자기 분위기 고급 야구 ㄷㄷ"
    },
    {
      "comment_after_openDate": "05:29:49",
      "score_difference": "39.28",
      "text": "답답한데 계속 보게 되네 ㅋㅋ",
      "image_text": "답답한데 계속 보게 되네 ㅋㅋ"
    },
    {
      "comment_after_openDate": "05:35:03",
      "score_difference": "42.02",
      "text": "이걸 진짜 홈런 치네 캬",
      "image_text": "이걸 진짜 홈런 치네 캬"
    },
    {
      "comment_after_openDate": "05:35:43",
      "score_difference": "52.41",
      "text": "형이 교육 제대로 했네 ㅋㅋㅋ",
      "image_text": "형이 교육 제대로 했네 ㅋㅋㅋ"
    },
    {
      "comment_after_openDate": "05:37:38",
      "score_difference": "33.12",
      "text": "드디어 흐름 타기 시작했다 ㅋㅋ",
      "image_text": "드디어 흐름 타기 시작했다 ㅋㅋ"
    },
    {
      "comment_after_openDate": "05:39:58",
      "score_difference": "42.43",
      "text": "와 이걸 그냥 담궈버린다고?",
      "image_text": "와 이걸 그냥 담궈버린다고?"
    },
    {
      "comment_after_openDate": "05:47:12",
      "score_difference": "31.21",
      "text": "발 다쳤는데 왜 안 쉬냐고 ㅋㅋ",
      "image_text": "발 다쳤는데 왜 안 쉬냐고 ㅋㅋ"
    },
    {
      "comment_after_openDate": "05:48:22",
      "score_difference": "54.36",
      "text": "과거 얘기로 기 싸움 오지네",
      "image_text": "과거 얘기로 기 싸움 오지네"
    },
    {
      "comment_after_openDate": "05:50:07",
      "score_difference": "35.17",
      "text": "혼자 꿀 빨다 온 거 보소 ㅋㅋ",
      "image_text": "혼자 꿀 빨다 온 거 보소 ㅋㅋ"
    },
    {
      "comment_after_openDate": "05:52:55",
      "score_difference": "32.98",
      "text": "그러다 감기 걸린다 조심해라",
      "image_text": "그러다 감기 걸린다 조심해라"
    },
    {
      "comment_after_openDate": "05:53:55",
      "score_difference": "34.70",
      "text": "까까머리들 수준 실화냐 ㅋㅋ",
      "image_text": "까까머리들 수준 실화냐 ㅋㅋ"
    },
    {
      "comment_after_openDate": "05:55:06",
      "score_difference": "36.66",
      "text": "오 뭔가 보여주나? ㄷㄷ",
      "image_text": "오 뭔가 보여주나? ㄷㄷ"
    },
    {
      "comment_after_openDate": "05:55:56",
      "score_difference": "35.77",
      "text": "어그로 끄는 거 전통이냐고 ㅋㅋ",
      "image_text": "어그로 끄는 거 전통이냐고 ㅋㅋ"
    },
    {
      "comment_after_openDate": "06:01:50",
      "score_difference": "56.00",
      "text": "완전 시쪽이 다 됐네 ㅋㅋㅋ",
      "image_text": "완전 시쪽이 다 됐네 ㅋㅋㅋ"
    },
    {
      "comment_after_openDate": "06:03:26",
      "score_difference": "43.81",
      "text": "이제 슬슬 잘 시간인가 보네",
      "image_text": "이제 슬슬 잘 시간인가 보네"
    }
  ],
  "statistics": {
    "total_highlights": 120,
    "total_with_scores": 115,
    "avg_score": 42.38,
    "max_score": 75.55,
    "min_score": 25.74,
    "big_highlights": 9,
    "score_ranges": {
      "0-20": 0,
      "21-40": 60,
      "41-60": 43,
      "61-80": 12,
      "81-100": 0
    }
  }
}